{
  "D20.sch.json": {
    "by_type": {
      "decoupling": 1,
      "rc_filter": 1,
      "voltage_divider": 4
    },
    "fail": 0,
    "pass": 4,
    "pass_rate": 66.7,
    "skip": 2,
    "total_sims": 6,
    "warn": 0
  },
  "D20cpu.sch.json": {
    "by_type": {},
    "fail": 0,
    "pass": 0,
    "pass_rate": 0,
    "skip": 0,
    "total_sims": 0,
    "warn": 0
  },
  "D20pwr.sch.json": {
    "by_type": {
      "decoupling": 1,
      "rc_filter": 1,
      "voltage_divider": 2
    },
    "fail": 0,
    "pass": 4,
    "pass_rate": 100.0,
    "skip": 0,
    "total_sims": 4,
    "warn": 0
  },
  "D20rcm.sch.json": {
    "by_type": {},
    "fail": 0,
    "pass": 0,
    "pass_rate": 0,
    "skip": 0,
    "total_sims": 0,
    "warn": 0
  }
}
