{
  "filename_aliases": [
    "ST4118M1206.pdf"
  ],
  "first_seen": "2026-04-11T17:10:50Z",
  "found_in": [
    {
      "first_seen": "2026-04-11T17:10:50Z",
      "path": "/home/aklofas/Projects/kicad-happy-testharness/repos/Hal9k-dk/lasersaur/datasheets/steppers/ST4118M1206.pdf",
      "ref": "Hal9k-dk/lasersaur",
      "type": "repo"
    }
  ],
  "last_seen": "2026-04-11T17:10:50Z",
  "manufacturers": [
    "STMicroelectronics"
  ],
  "mpns": [
    {
      "mpn": "ST4118M1206",
      "primary": true
    }
  ],
  "page_count": null,
  "revision_label": null,
  "sha256": "5e3b0e897b38896423d6904cb1c246e241accb9256debec5ce0efac7dbaceaaa",
  "size_bytes": 146349,
  "source_urls": [],
  "verification_notes": null,
  "verified": false
}
