{
  "Fuente.sch.json": {
    "bom_lines": 0,
    "component_types": {},
    "erc_warning_count": 0,
    "sections": [
      "analyzer_type",
      "annotation_issues",
      "audience_summary",
      "bom",
      "components",
      "design_analysis",
      "design_intent",
      "file_version",
      "findings",
      "kicad_version",
      "labels",
      "legacy_analysis_quality",
      "nets",
      "no_connects",
      "power_sequencing_validation",
      "power_symbols",
      "rail_voltages",
      "schema_version",
      "sheet_files",
      "sheets_parsed",
      "statistics",
      "subcircuits",
      "summary",
      "trust_summary"
    ],
    "signal_counts": {
      "suggest_certifications": 2
    },
    "total_components": 0,
    "total_labels": 0,
    "total_nets": 0,
    "total_power_symbols": 0
  },
  "IO_Principal.sch.json": {
    "bom_lines": 8,
    "component_types": {
      "capacitor": 1,
      "connector": 2,
      "diode": 2,
      "fuse": 1,
      "ic": 6
    },
    "erc_warning_count": 2,
    "sections": [
      "analyzer_type",
      "annotation_issues",
      "audience_summary",
      "bom",
      "components",
      "design_analysis",
      "design_intent",
      "file_version",
      "findings",
      "kicad_version",
      "labels",
      "legacy_analysis_quality",
      "nets",
      "no_connects",
      "power_sequencing_validation",
      "power_symbols",
      "rail_voltages",
      "schema_version",
      "sheet_files",
      "sheets_parsed",
      "statistics",
      "subcircuits",
      "summary",
      "trust_summary"
    ],
    "signal_counts": {
      "audit_connector_ground_distribution": 1,
      "audit_esd_protection": 1,
      "audit_rail_sources": 2,
      "detect_design_observations": 2,
      "suggest_certifications": 2
    },
    "total_components": 9,
    "total_labels": 0,
    "total_nets": 85,
    "total_power_symbols": 0
  },
  "Inyectores%2fEncendido.sch.json": {
    "bom_lines": 5,
    "component_types": {
      "diode": 6,
      "resistor": 12,
      "transistor": 18
    },
    "erc_warning_count": 0,
    "sections": [
      "analyzer_type",
      "annotation_issues",
      "audience_summary",
      "bom",
      "components",
      "design_analysis",
      "design_intent",
      "file_version",
      "findings",
      "kicad_version",
      "labels",
      "legacy_analysis_quality",
      "nets",
      "no_connects",
      "power_sequencing_validation",
      "power_symbols",
      "rail_voltages",
      "schema_version",
      "sheet_files",
      "sheets_parsed",
      "statistics",
      "subcircuits",
      "summary",
      "trust_summary"
    ],
    "signal_counts": {
      "detect_transistor_circuits": 12,
      "suggest_certifications": 2
    },
    "total_components": 36,
    "total_labels": 0,
    "total_nets": 40,
    "total_power_symbols": 0
  },
  "Relay.sch.json": {
    "bom_lines": 6,
    "component_types": {
      "diode": 6,
      "ic": 2,
      "resistor": 8,
      "transistor": 6
    },
    "erc_warning_count": 0,
    "sections": [
      "analyzer_type",
      "annotation_issues",
      "audience_summary",
      "bom",
      "components",
      "design_analysis",
      "design_intent",
      "file_version",
      "findings",
      "kicad_version",
      "labels",
      "legacy_analysis_quality",
      "nets",
      "no_connects",
      "power_sequencing_validation",
      "power_symbols",
      "rail_voltages",
      "schema_version",
      "sheet_files",
      "sheets_parsed",
      "statistics",
      "subcircuits",
      "summary",
      "trust_summary"
    ],
    "signal_counts": {
      "audit_rail_sources": 1,
      "detect_design_observations": 1,
      "detect_opamp_circuits": 1,
      "detect_transistor_circuits": 6,
      "detect_voltage_dividers": 1,
      "suggest_certifications": 2
    },
    "total_components": 21,
    "total_labels": 0,
    "total_nets": 37,
    "total_power_symbols": 0
  },
  "Sensores.sch.json": {
    "bom_lines": 10,
    "component_types": {
      "capacitor": 20,
      "diode": 8,
      "ic": 3,
      "resistor": 22
    },
    "erc_warning_count": 1,
    "sections": [
      "analyzer_type",
      "annotation_issues",
      "audience_summary",
      "bom",
      "components",
      "design_analysis",
      "design_intent",
      "file_version",
      "findings",
      "kicad_version",
      "labels",
      "legacy_analysis_quality",
      "nets",
      "no_connects",
      "power_sequencing_validation",
      "power_symbols",
      "rail_voltages",
      "schema_version",
      "sheet_files",
      "sheets_parsed",
      "statistics",
      "subcircuits",
      "summary",
      "trust_summary"
    ],
    "signal_counts": {
      "audit_rail_sources": 1,
      "detect_opamp_circuits": 2,
      "detect_voltage_dividers": 2,
      "suggest_certifications": 2
    },
    "total_components": 52,
    "total_labels": 0,
    "total_nets": 57,
    "total_power_symbols": 0
  },
  "v2.sch.json": {
    "bom_lines": 38,
    "component_types": {
      "capacitor": 21,
      "connector": 8,
      "diode": 26,
      "fuse": 1,
      "ic": 13,
      "jumper": 1,
      "led": 5,
      "resistor": 51,
      "switch": 4,
      "transistor": 25
    },
    "erc_warning_count": 13,
    "sections": [
      "analyzer_type",
      "annotation_issues",
      "audience_summary",
      "bom",
      "components",
      "design_analysis",
      "design_intent",
      "file_version",
      "findings",
      "kicad_version",
      "labels",
      "legacy_analysis_quality",
      "nets",
      "no_connects",
      "power_sequencing_validation",
      "power_symbols",
      "rail_voltages",
      "schema_version",
      "sheet_files",
      "sheets_parsed",
      "statistics",
      "subcircuits",
      "summary",
      "trust_summary"
    ],
    "signal_counts": {
      "audit_connector_ground_distribution": 5,
      "audit_esd_protection": 7,
      "audit_led_circuits": 5,
      "audit_rail_sources": 4,
      "detect_design_observations": 8,
      "detect_opamp_circuits": 2,
      "detect_solder_jumpers": 1,
      "detect_transistor_circuits": 25,
      "detect_voltage_dividers": 4,
      "suggest_certifications": 2,
      "validate_pullups": 2
    },
    "total_components": 149,
    "total_labels": 0,
    "total_nets": 320,
    "total_power_symbols": 0
  },
  "v2_1.sch.json": {
    "bom_lines": 17,
    "component_types": {
      "connector": 6,
      "diode": 4,
      "ic": 2,
      "jumper": 1,
      "led": 5,
      "resistor": 9,
      "switch": 4,
      "transistor": 1
    },
    "erc_warning_count": 0,
    "sections": [
      "analyzer_type",
      "annotation_issues",
      "audience_summary",
      "bom",
      "components",
      "design_analysis",
      "design_intent",
      "file_version",
      "findings",
      "kicad_version",
      "labels",
      "legacy_analysis_quality",
      "nets",
      "no_connects",
      "power_sequencing_validation",
      "power_symbols",
      "rail_voltages",
      "schema_version",
      "sheet_files",
      "sheets_parsed",
      "statistics",
      "subcircuits",
      "summary",
      "trust_summary"
    ],
    "signal_counts": {
      "audit_connector_ground_distribution": 4,
      "audit_esd_protection": 6,
      "audit_led_circuits": 5,
      "audit_rail_sources": 3,
      "detect_design_observations": 6,
      "detect_solder_jumpers": 1,
      "detect_transistor_circuits": 1,
      "detect_voltage_dividers": 1,
      "suggest_certifications": 2,
      "validate_pullups": 2
    },
    "total_components": 32,
    "total_labels": 0,
    "total_nets": 162,
    "total_power_symbols": 0
  }
}
