{
  "filename_aliases": [
    "RC6802 CPU.pdf"
  ],
  "first_seen": "2026-04-11T17:10:50Z",
  "found_in": [
    {
      "first_seen": "2026-04-11T17:10:50Z",
      "path": "/home/aklofas/Projects/kicad-happy-testharness/repos/tebl/RC6802-Microchicken/RC6802 CPU/export/RC6802 CPU.pdf",
      "ref": "tebl/RC6802-Microchicken",
      "type": "repo"
    }
  ],
  "last_seen": "2026-04-11T17:10:50Z",
  "manufacturers": [
    "Unknown"
  ],
  "mpns": [
    {
      "mpn": "RC6802",
      "primary": true
    }
  ],
  "page_count": null,
  "revision_label": null,
  "sha256": "298f3e654405868404d8c60f762c240c421e2ecc01568b46ea479a24d943c0b9",
  "size_bytes": 124120,
  "source_urls": [],
  "verification_notes": null,
  "verified": false
}
