{
  "button-board_button-board_button-board.kicad_sch.json": {
    "by_category": {
      "board_edge": 1,
      "ground_plane": 1,
      "io_filtering": 2
    },
    "critical": 0,
    "emc_risk_score": 92,
    "high": 0,
    "low": 2,
    "medium": 2,
    "target_standard": "fcc-class-b",
    "total_findings": 4
  },
  "debug.kicad_sch.json": {
    "by_category": {},
    "critical": 0,
    "emc_risk_score": 100,
    "high": 0,
    "low": 0,
    "medium": 0,
    "target_standard": "fcc-class-b",
    "total_findings": 0
  },
  "io.kicad_sch.json": {
    "by_category": {},
    "critical": 0,
    "emc_risk_score": 100,
    "high": 0,
    "low": 0,
    "medium": 0,
    "target_standard": "fcc-class-b",
    "total_findings": 0
  },
  "mcu.kicad_sch.json": {
    "by_category": {},
    "critical": 0,
    "emc_risk_score": 100,
    "high": 0,
    "low": 0,
    "medium": 0,
    "target_standard": "fcc-class-b",
    "total_findings": 0
  },
  "power.kicad_sch.json": {
    "by_category": {},
    "critical": 0,
    "emc_risk_score": 100,
    "high": 0,
    "low": 0,
    "medium": 0,
    "target_standard": "fcc-class-b",
    "total_findings": 0
  },
  "single_button.kicad_sch.json": {
    "by_category": {},
    "critical": 0,
    "emc_risk_score": 100,
    "high": 0,
    "low": 0,
    "medium": 0,
    "target_standard": "fcc-class-b",
    "total_findings": 0
  },
  "syrup.kicad_sch.json": {
    "by_category": {
      "via_stitching": 1
    },
    "critical": 0,
    "emc_risk_score": 97,
    "high": 0,
    "low": 0,
    "medium": 1,
    "target_standard": "fcc-class-b",
    "total_findings": 1
  },
  "usb_connector.kicad_sch.json": {
    "by_category": {},
    "critical": 0,
    "emc_risk_score": 100,
    "high": 0,
    "low": 0,
    "medium": 0,
    "target_standard": "fcc-class-b",
    "total_findings": 0
  }
}
