{
  "Djinn.sch.json": {
    "by_type": {
      "decoupling": 4,
      "protection_device": 2,
      "rc_filter": 4,
      "transistor_circuit": 6,
      "voltage_divider": 3
    },
    "fail": 0,
    "pass": 16,
    "pass_rate": 84.2,
    "skip": 2,
    "total_sims": 19,
    "warn": 1
  },
  "ExtraBoard-Base_ExtraBoard-Base.sch.json": {
    "by_type": {},
    "fail": 0,
    "pass": 0,
    "pass_rate": 0,
    "skip": 0,
    "total_sims": 0,
    "warn": 0
  },
  "ExtraBoard-Plate_ExtraBoard-Plate.sch.json": {
    "by_type": {},
    "fail": 0,
    "pass": 0,
    "pass_rate": 0,
    "skip": 0,
    "total_sims": 0,
    "warn": 0
  }
}
