{
  "findings": [
    {
      "analyzer_type": "schematic",
      "source_file": "BeagleV_BeagleV.kicad_sch.json",
      "status": "new",
      "summary": "BeagleV v0.7 RISC-V SBC (VIC-V10 SoC, LPDDR4, USB3 hub, Ethernet, HDMI, WiFi/BT) - 19-sheet hierarchical design with 643 components; good signal detection for crystals, RC filters, I2C, and one voltage divider; missed LPDDR4 memory interfaces, misidentified HDMI connector and TPS65086100 feedback, LMR62014 Vref wrong",
      "correct": [
        {
          "description": "Correctly identified 5 crystal circuits (X1, X3, X4, X6, X?) with load capacitors and effective load pF calculations",
          "analyzer_section": "signal_analysis.crystal_circuits",
          "check": {
            "path": "signal_analysis.crystal_circuits",
            "op": "contains_match",
            "field": "reference",
            "pattern": "^X1$"
          },
          "detector": "crystal_circuits",
          "subject_refs": [
            "X1",
            "X3",
            "X4",
            "X6"
          ],
          "expected_relation": "in_detector",
          "confidence": 0.9
        },
        {
          "description": "Correctly detected 8 RC filter networks in the audio DAC output section (R265-R272 with C309-C314)",
          "analyzer_section": "signal_analysis.rc_filters",
          "check": {
            "path": "signal_analysis.rc_filters",
            "op": "contains_match",
            "field": "resistor.ref",
            "pattern": "^R265$"
          },
          "detector": "rc_filters",
          "subject_refs": [
            "C309",
            "C310",
            "C311",
            "C312",
            "C313",
            "C314",
            "R265",
            "R266",
            "R267",
            "R268",
            "R269",
            "R270",
            "R271",
            "R272"
          ],
          "expected_relation": "in_detector",
          "confidence": 0.9
        },
        {
          "description": "Correctly identified R261/R264 voltage divider (49.9K/13.3K) as feedback for U13 LMR62014 boost converter",
          "analyzer_section": "signal_analysis.voltage_dividers",
          "check": {
            "path": "signal_analysis.voltage_dividers",
            "op": "contains_match",
            "field": "r_top.ref",
            "pattern": "^R261$"
          },
          "detector": "voltage_dividers",
          "subject_refs": [
            "R261",
            "R264",
            "U13"
          ],
          "expected_relation": "in_detector",
          "confidence": 0.9
        },
        {
          "description": "Correctly detected 4 I2C buses (I2C0 SCL/SDA, I2C2 SCL/SDA) with pull-up resistors and connected devices",
          "analyzer_section": "signal_analysis.design_observations",
          "check": {
            "path": "signal_analysis.design_observations",
            "op": "min_count",
            "value": 1
          },
          "detector": "design_observations",
          "subject_refs": [],
          "expected_relation": "in_detector",
          "confidence": 0.7
        },
        {
          "description": "Correctly detected Ethernet PHY U5 (KSZ9031RNXCA) in ethernet_interfaces",
          "analyzer_section": "signal_analysis.ethernet_interfaces",
          "check": {
            "path": "signal_analysis.ethernet_interfaces",
            "op": "contains_match",
            "field": "phy_reference",
            "pattern": "^U5$"
          },
          "detector": "ethernet_interfaces",
          "subject_refs": [
            "U5"
          ],
          "expected_relation": "in_detector",
          "confidence": 0.9
        },
        {
          "description": "Correctly identified 2 power regulators: U13 (LMR62014 switching) and U14 (TPS65086100 PMIC)",
          "analyzer_section": "signal_analysis.power_regulators",
          "check": {
            "path": "signal_analysis.power_regulators",
            "op": "contains_match",
            "field": "ref",
            "pattern": "^U13$"
          },
          "detector": "power_regulators",
          "subject_refs": [
            "U13",
            "U14"
          ],
          "expected_relation": "in_detector",
          "confidence": 0.9
        },
        {
          "description": "Correctly identified J13 as USB Type-C connector with passing CC1/CC2 5.1K pulldown checks",
          "analyzer_section": "usb_compliance",
          "check": {
            "path": "usb_compliance.summary.pass",
            "op": "min_value",
            "value": 2
          }
        },
        {
          "description": "Correctly detected RF matching network for ANT1 antenna (RFECA3216060A1T) with L3 10nH and C213 1pF",
          "analyzer_section": "signal_analysis.rf_matching",
          "check": {
            "path": "signal_analysis.rf_matching",
            "op": "min_count",
            "value": 1
          },
          "detector": "rf_matching",
          "subject_refs": [
            "C213",
            "L3"
          ],
          "expected_relation": "in_detector",
          "confidence": 0.9
        },
        {
          "description": "Correctly identified 6 protection devices including TVS diodes (D1, D2, D4, D5), Schottky (D52 SMBJ5.0CA), and fuse F2",
          "analyzer_section": "signal_analysis.protection_devices",
          "check": {
            "path": "signal_analysis.protection_devices",
            "op": "contains_match",
            "field": "ref",
            "pattern": "^D1$"
          },
          "detector": "protection_devices",
          "subject_refs": [
            "D1",
            "D2",
            "D4",
            "D5",
            "D52",
            "F2"
          ],
          "expected_relation": "in_detector",
          "confidence": 0.9
        },
        {
          "description": "Correctly detected 4 MOSFET transistor circuits: Q1/Q3 (CJ1012 LED drivers), Q8 (IRLML6401 P-ch power switch), Q2 (USB power control)",
          "analyzer_section": "signal_analysis.transistor_circuits",
          "check": {
            "path": "signal_analysis.transistor_circuits",
            "op": "contains_match",
            "field": "reference",
            "pattern": "^Q1$"
          },
          "detector": "transistor_circuits",
          "subject_refs": [
            "Q1",
            "Q2",
            "Q3",
            "Q8"
          ],
          "expected_relation": "in_detector",
          "confidence": 0.9
        },
        {
          "description": "Total component count of 643 is consistent with 640 unique non-power references across 19 hierarchical sheets",
          "analyzer_section": "statistics",
          "check": {
            "path": "statistics.total_components",
            "op": "min_value",
            "value": 640
          }
        },
        {
          "description": "Correctly identified 19 hierarchical sheets in this complex SBC design",
          "analyzer_section": "sheets",
          "check": {
            "path": "sheets",
            "op": "min_count",
            "value": 19
          }
        },
        {
          "description": "Decoupling analysis correctly identified 5 power rails with capacitor coverage details",
          "analyzer_section": "signal_analysis.decoupling_analysis",
          "check": {
            "path": "signal_analysis.decoupling_analysis",
            "op": "min_count",
            "value": 1
          },
          "detector": "decoupling_analysis",
          "subject_refs": [],
          "expected_relation": "in_detector",
          "confidence": 0.7
        }
      ],
      "incorrect": [
        {
          "description": "LMR62014 (U13) has both input_rail and output_rail set to +5V, which is impossible for a boost converter; the input should be a lower voltage rail (CTL5 or similar) and output should be VSYS_5V8/+5V",
          "analyzer_section": "signal_analysis.power_regulators",
          "check": {
            "path": "signal_analysis.power_regulators",
            "op": "not_contains_match",
            "field": "ref",
            "pattern": "^U13$"
          },
          "detector": "power_regulators",
          "subject_refs": [
            "U13"
          ],
          "expected_relation": "not_in_detector",
          "confidence": 0.9
        },
        {
          "description": "TPS65086100 (U14) feedback_divider incorrectly identifies R100=100K and R167=4.7K as its feedback network; these are actually gate resistors for Q3 (CJ1012 LED driver MOSFET), not feedback for the PMIC which uses internally-set voltages",
          "analyzer_section": "signal_analysis.power_regulators",
          "check": {
            "path": "signal_analysis.power_regulators",
            "op": "not_contains_match",
            "field": "ref",
            "pattern": "^U14$"
          },
          "detector": "power_regulators",
          "subject_refs": [
            "Q3",
            "R100",
            "R167",
            "U14"
          ],
          "expected_relation": "not_in_detector",
          "confidence": 0.9
        },
        {
          "description": "LMR62014 estimated_vout of 2.851V uses assumed Vref=0.6V, but the LMR62014 datasheet specifies Vref=1.233V; correct Vout would be ~5.86V (matching VSYS_5V8 rail)",
          "analyzer_section": "signal_analysis.power_regulators",
          "detector": "power_regulators",
          "subject_refs": [],
          "expected_relation": "not_in_detector",
          "confidence": 0.7
        },
        {
          "description": "HDMI interface detection found P? (HDMI_1V8 power symbol) as the HDMI connector instead of J11 (ST-HD-010 actual HDMI connector) and missed U11 (TDA19988 HDMI transmitter IC) as the encoder",
          "analyzer_section": "signal_analysis.hdmi_dvi_interfaces",
          "check": {
            "path": "signal_analysis.hdmi_dvi_interfaces",
            "op": "not_contains_match",
            "field": "connector",
            "pattern": "^J11$"
          },
          "detector": "hdmi_dvi_interfaces",
          "subject_refs": [
            "J11",
            "U11"
          ],
          "expected_relation": "not_in_detector",
          "confidence": 0.9
        },
        {
          "description": "Ethernet interface found U5 (KSZ9031RNXCA) but shows empty magnetics and connectors arrays; J6 (LPJG0801HBNL RJ45 with integrated magnetics) should be detected as the connector",
          "analyzer_section": "signal_analysis.ethernet_interfaces",
          "check": {
            "path": "signal_analysis.ethernet_interfaces",
            "op": "not_contains_match",
            "field": "phy_reference",
            "pattern": "^J6$"
          },
          "detector": "ethernet_interfaces",
          "subject_refs": [
            "J6",
            "U5"
          ],
          "expected_relation": "not_in_detector",
          "confidence": 0.9
        },
        {
          "description": "IC pin analysis reports 0 connected pins for all 96 IC entries despite signal detectors successfully resolving net connectivity - systematic failure in pin connectivity counting",
          "analyzer_section": "ic_pin_analysis"
        },
        {
          "description": "OSC1 (32.768kHz-clock oscillator module) classified as type=other; should be classified as oscillator or crystal",
          "analyzer_section": "statistics.component_types"
        }
      ],
      "missed": [
        {
          "description": "LPDDR4 memory interfaces not detected: U7 and U8 (32Gbit_RAM) are LPDDR4 chips with full address/data bus connections to U9 (VIC-V10 SoC)",
          "analyzer_section": "signal_analysis.memory_interfaces",
          "check": {
            "path": "signal_analysis.memory_interfaces",
            "op": "contains_match",
            "field": "memory_reference",
            "pattern": "^U7$"
          },
          "detector": "memory_interfaces",
          "subject_refs": [
            "U7",
            "U8",
            "U9"
          ],
          "expected_relation": "in_detector",
          "confidence": 0.9
        },
        {
          "description": "USB 3.0 hub (U1 GL3520-OS322) not identified as a bus hub/repeater in any signal analysis section; it connects upstream USB from VIC SoC to two downstream USB 3.0 Type-A ports",
          "analyzer_section": "signal_analysis.design_observations",
          "check": {
            "path": "signal_analysis.design_observations",
            "op": "min_count",
            "value": 1
          },
          "detector": "design_observations",
          "subject_refs": [
            "U1"
          ],
          "expected_relation": "in_detector",
          "confidence": 0.9
        },
        {
          "description": "PCMF2USB3S USB3 ESD protection ICs (D27-D32, 6 devices) not detected in protection_devices despite being dedicated USB ESD suppressors on the Type-A port data lines",
          "analyzer_section": "signal_analysis.protection_devices",
          "check": {
            "path": "signal_analysis.protection_devices",
            "op": "contains_match",
            "field": "ref",
            "pattern": "^D27$"
          },
          "detector": "protection_devices",
          "subject_refs": [
            "D27",
            "D28",
            "D29",
            "D30",
            "D31",
            "D32"
          ],
          "expected_relation": "in_detector",
          "confidence": 0.9
        },
        {
          "description": "WiFi/BT combo module U12 (AP6236) not specifically identified in any signal analysis section; has dedicated 26MHz crystal (X4), antenna matching network, and SDIO/UART interfaces",
          "analyzer_section": "signal_analysis.design_observations",
          "check": {
            "path": "signal_analysis.design_observations",
            "op": "min_count",
            "value": 1
          },
          "detector": "design_observations",
          "subject_refs": [
            "U12",
            "X4"
          ],
          "expected_relation": "in_detector",
          "confidence": 0.9
        },
        {
          "description": "Q6 and Q7 (CSD87381P NexFET power MOSFETs) used as external power stages for TPS65086100 PMIC not detected in transistor_circuits",
          "analyzer_section": "signal_analysis.transistor_circuits",
          "check": {
            "path": "signal_analysis.transistor_circuits",
            "op": "contains_match",
            "field": "reference",
            "pattern": "^Q6$"
          },
          "detector": "transistor_circuits",
          "subject_refs": [
            "Q6",
            "Q7"
          ],
          "expected_relation": "in_detector",
          "confidence": 0.9
        },
        {
          "description": "Q9 (BCM857BS-7F-F dual PNP transistor) used in USB VBUS/OTG detection circuit not detected in transistor_circuits",
          "analyzer_section": "signal_analysis.transistor_circuits",
          "check": {
            "path": "signal_analysis.transistor_circuits",
            "op": "contains_match",
            "field": "reference",
            "pattern": "^Q9$"
          },
          "detector": "transistor_circuits",
          "subject_refs": [
            "Q9"
          ],
          "expected_relation": "in_detector",
          "confidence": 0.9
        },
        {
          "description": "Multiple custom power domains from P? power flag symbols (VSYS_5V8, VCC_0V9, LDO_3V3, 3V3_WIFI, AVDD09_PLL, VETH1_DVDDH/AVDDH) not captured in power_rails",
          "analyzer_section": "statistics.power_rails",
          "check": {
            "path": "statistics.power_rails",
            "op": "min_count",
            "value": 1
          }
        },
        {
          "description": "D65 (PMEG3010CEJ) is a Schottky catch diode for LMR62014 boost converter but not linked to the regulator circuit or identified in protection_devices",
          "analyzer_section": "signal_analysis.protection_devices",
          "check": {
            "path": "signal_analysis.protection_devices",
            "op": "contains_match",
            "field": "ref",
            "pattern": "^D65$"
          },
          "detector": "protection_devices",
          "subject_refs": [
            "D65"
          ],
          "expected_relation": "in_detector",
          "confidence": 0.9
        }
      ],
      "suggestions": [
        "Improve HDMI detection to associate TDA19988 (HDMI encoder IC) with the actual HDMI connector J11 instead of power flag symbols",
        "Add LPDDR4 memory interface detection: identify RAM ICs by part name pattern (xxGbit_RAM, DDR, LPDDR) and their address/data buses",
        "Detect integrated magnetics RJ45 connectors like LPJG0801HBNL to populate ethernet_interfaces.connectors",
        "For PMICs like TPS65086100, do not assign external feedback dividers when the device uses internally-set output voltages",
        "Recognize PCMF2USB3S and similar multi-channel USB ESD protection ICs in protection_devices",
        "Improve Vref heuristics for boost converters: LMR62014 uses 1.233V reference, not 0.6V; consider using a lookup table for common regulator ICs",
        "Detect NexFET/power MOSFET pairs (CSD87381P) associated with PMIC ICs as part of the regulator subcircuit",
        "Recognize custom power domain symbols (P? with values like VCC_0V9, 3V3_WIFI) as additional power rails"
      ],
      "related_issues": [],
      "should_become_assertion": true,
      "repo": "aswinvenu/beaglev-kicad",
      "project": "BeagleV_BeagleV",
      "created": "2026-03-23T18:11:45.313880+00:00",
      "datasheets_used": [],
      "id": "FND-00002593"
    }
  ]
}
