{
  "filename_aliases": [
    "KW4-566CAB.pdf"
  ],
  "first_seen": "2026-04-11T17:10:50Z",
  "found_in": [
    {
      "first_seen": "2026-04-11T17:10:50Z",
      "path": "/home/aklofas/Projects/kicad-happy-testharness/repos/mprosk/mtg_life_counter/datasheets/led_tht/KW4-566CAB.pdf",
      "ref": "mprosk/mtg_life_counter",
      "type": "repo"
    }
  ],
  "last_seen": "2026-04-11T17:10:50Z",
  "manufacturers": [
    "Unknown"
  ],
  "mpns": [
    {
      "mpn": "KW4_566CAB",
      "primary": true
    }
  ],
  "page_count": null,
  "revision_label": null,
  "sha256": "982cf257df3228bafc4f24f63488c27115d377dd7f48bf19b98a1858bea1ed8d",
  "size_bytes": 277974,
  "source_urls": [],
  "verification_notes": null,
  "verified": false
}
