{
  "filename_aliases": [
    "26-302x_layout.pdf"
  ],
  "first_seen": "2026-04-11T17:10:50Z",
  "found_in": [
    {
      "first_seen": "2026-04-11T17:10:50Z",
      "path": "/home/aklofas/Projects/kicad-happy-testharness/repos/qbancoffee/coco_motherboards/pdfs/26-302x_layout.pdf",
      "ref": "qbancoffee/coco_motherboards",
      "type": "repo"
    }
  ],
  "last_seen": "2026-04-11T17:10:50Z",
  "manufacturers": [
    "Unknown"
  ],
  "mpns": [
    {
      "mpn": "26_302X_LAYOUT",
      "primary": true
    }
  ],
  "page_count": null,
  "revision_label": null,
  "sha256": "9851b08c5679b15b6c16bb5167239a554859964ff7b4c39120775c58da2247f4",
  "size_bytes": 263359,
  "source_urls": [],
  "verification_notes": null,
  "verified": false
}
