{
  "filename_aliases": [
    "fabrication.pdf"
  ],
  "first_seen": "2026-04-11T17:10:50Z",
  "found_in": [
    {
      "first_seen": "2026-04-11T17:10:50Z",
      "path": "/home/aklofas/Projects/kicad-happy-testharness/repos/GlasgowEmbedded/glasgow/hardware/boards/glasgow/revB/fabrication.pdf",
      "ref": "GlasgowEmbedded/glasgow",
      "type": "repo"
    }
  ],
  "last_seen": "2026-04-11T17:10:50Z",
  "manufacturers": [
    "Unknown"
  ],
  "mpns": [
    {
      "mpn": "FABRICATION",
      "primary": true
    }
  ],
  "page_count": null,
  "revision_label": null,
  "sha256": "8e80d5e85a7b2b616e1b07f26136b8d82713cc73a65514f05e047ad7d63b83b5",
  "size_bytes": 136978,
  "source_urls": [],
  "verification_notes": null,
  "verified": false
}
