{
  "filename_aliases": [
    "Formation_2020_bras_robot.pdf"
  ],
  "first_seen": "2026-04-11T17:10:50Z",
  "found_in": [
    {
      "first_seen": "2026-04-11T17:10:50Z",
      "path": "/home/aklofas/Projects/kicad-happy-testharness/repos/AssociationRobotTelecomStrasbourg/Formation_RobotArm/Formation_2020_bras_robot.pdf",
      "ref": "AssociationRobotTelecomStrasbourg/Formation_RobotArm",
      "type": "repo"
    }
  ],
  "last_seen": "2026-04-11T17:10:50Z",
  "manufacturers": [
    "Unknown"
  ],
  "mpns": [
    {
      "mpn": "FORMATION_2020_BRAS_ROBOT",
      "primary": true
    }
  ],
  "page_count": null,
  "revision_label": null,
  "sha256": "8ee9780be911ecd852d6259e44bb1f2e77ba4f5c543c92efd5f69b6c03dcb9cb",
  "size_bytes": 1225168,
  "source_urls": [],
  "verification_notes": null,
  "verified": false
}
