{
  "filename_aliases": [
    "usblc62.pdf"
  ],
  "first_seen": "2026-04-11T17:10:50Z",
  "found_in": [
    {
      "first_seen": "2026-04-11T17:10:50Z",
      "path": "/home/aklofas/Projects/kicad-happy-testharness/repos/blfp1/project-tarkus/datasheets/usblc62.pdf",
      "ref": "blfp1/project-tarkus",
      "type": "repo"
    }
  ],
  "last_seen": "2026-04-11T17:10:50Z",
  "manufacturers": [
    "Unknown"
  ],
  "mpns": [
    {
      "mpn": "USBLC62",
      "primary": true
    }
  ],
  "page_count": null,
  "revision_label": null,
  "sha256": "6f6ee112ff147ef1f22bac4dbd3cc7cea5d4e0cd6f47afc729c89b456e98d938",
  "size_bytes": 559144,
  "source_urls": [],
  "verification_notes": null,
  "verified": false
}
