{
  "filename_aliases": [
    "office_cabinet_3p_v2_south.pdf"
  ],
  "first_seen": "2026-04-11T17:10:50Z",
  "found_in": [
    {
      "first_seen": "2026-04-11T17:10:50Z",
      "path": "/home/aklofas/Projects/kicad-happy-testharness/repos/bgerp/ztm_doc/Cabinets/OfficeCabinetSouth/export/DEPRICATED/office_cabinet_3p_v2_south.pdf",
      "ref": "bgerp/ztm_doc",
      "type": "repo"
    }
  ],
  "last_seen": "2026-04-11T17:10:50Z",
  "manufacturers": [
    "Unknown"
  ],
  "mpns": [
    {
      "mpn": "OFFICE_CABINET_3P_V2_SOUTH",
      "primary": true
    }
  ],
  "page_count": null,
  "revision_label": null,
  "sha256": "c56e9d786d74e92695efc3b3442f177960cf1b29f76f0347520f494d527862b5",
  "size_bytes": 249050,
  "source_urls": [],
  "verification_notes": null,
  "verified": false
}
