{
  "filename_aliases": [
    "FT234XD-R.pdf"
  ],
  "first_seen": "2026-04-11T17:10:50Z",
  "found_in": [
    {
      "first_seen": "2026-04-11T17:10:50Z",
      "path": "/home/aklofas/Projects/kicad-happy-testharness/datasheets/FT234XD-R.pdf",
      "ref": "bulk",
      "type": "bulk"
    }
  ],
  "last_seen": "2026-04-11T17:10:50Z",
  "manufacturers": [
    "Unknown"
  ],
  "mpns": [
    {
      "mpn": "FT234XD_R",
      "primary": true
    }
  ],
  "page_count": null,
  "revision_label": null,
  "sha256": "ddd4ccc38d8dccbce58f234dd43b01b4c9bbbbb796a1f9b90e92fd1a47c3625c",
  "size_bytes": 706379,
  "source_urls": [],
  "verification_notes": null,
  "verified": false
}
