{
  "filename_aliases": [
    "reDIP-64-pcb.pdf"
  ],
  "first_seen": "2026-04-11T17:10:50Z",
  "found_in": [
    {
      "first_seen": "2026-04-11T17:10:50Z",
      "path": "/home/aklofas/Projects/kicad-happy-testharness/repos/daglem/reDIP-64/hardware/documentation/reDIP-64-pcb.pdf",
      "ref": "daglem/reDIP-64",
      "type": "repo"
    }
  ],
  "last_seen": "2026-04-11T17:10:50Z",
  "manufacturers": [
    "Unknown"
  ],
  "mpns": [
    {
      "mpn": "REDIP_64_PCB",
      "primary": true
    }
  ],
  "page_count": null,
  "revision_label": null,
  "sha256": "549c9df8798c947b9cbdaeaed57e9f2a674ba45dde9e0e0c950e2120fe6289aa",
  "size_bytes": 2496765,
  "source_urls": [],
  "verification_notes": null,
  "verified": false
}
