{
  "DCO.kicad_sch.json": {
    "by_type": {
      "decoupling": 3,
      "opamp_circuit": 9,
      "rc_filter": 4,
      "transistor_circuit": 2,
      "voltage_divider": 4
    },
    "fail": 0,
    "pass": 15,
    "pass_rate": 68.2,
    "skip": 0,
    "total_sims": 22,
    "warn": 7
  },
  "Filter.kicad_sch.json": {
    "by_type": {
      "decoupling": 5,
      "opamp_circuit": 3,
      "transistor_circuit": 2
    },
    "fail": 0,
    "pass": 7,
    "pass_rate": 70.0,
    "skip": 1,
    "total_sims": 10,
    "warn": 2
  },
  "VCAs.kicad_sch.json": {
    "by_type": {},
    "fail": 0,
    "pass": 0,
    "pass_rate": 0,
    "skip": 0,
    "total_sims": 0,
    "warn": 0
  },
  "VoiceBoardR5.kicad_sch.json": {
    "by_type": {
      "decoupling": 5,
      "opamp_circuit": 17,
      "rc_filter": 5,
      "transistor_circuit": 11,
      "voltage_divider": 6
    },
    "fail": 0,
    "pass": 30,
    "pass_rate": 68.2,
    "skip": 2,
    "total_sims": 44,
    "warn": 12
  },
  "Wavefolder.kicad_sch.json": {
    "by_type": {
      "decoupling": 2,
      "opamp_circuit": 5,
      "rc_filter": 1,
      "transistor_circuit": 7,
      "voltage_divider": 2
    },
    "fail": 0,
    "pass": 13,
    "pass_rate": 76.5,
    "skip": 1,
    "total_sims": 17,
    "warn": 3
  }
}
