{
  "filename_aliases": [
    "200-1-741899.pdf"
  ],
  "first_seen": "2026-04-11T17:10:50Z",
  "found_in": [
    {
      "first_seen": "2026-04-11T17:10:50Z",
      "path": "/home/aklofas/Projects/kicad-happy-testharness/repos/hkzlab/CGA_Redux/docs/200-1-741899.pdf",
      "ref": "hkzlab/CGA_Redux",
      "type": "repo"
    }
  ],
  "last_seen": "2026-04-11T17:10:50Z",
  "manufacturers": [
    "Unknown"
  ],
  "mpns": [
    {
      "mpn": "200_1_741899",
      "primary": true
    }
  ],
  "page_count": null,
  "revision_label": null,
  "sha256": "4048a908edda271547b02f2ea1644acdc4c0a0e272e2078c68cd4da13c040070",
  "size_bytes": 245556,
  "source_urls": [],
  "verification_notes": null,
  "verified": false
}
